MANIFEST.in
README.md
setup.cfg
setup.py
strpy/__init__.py
strpy/calibration.py
strpy.egg-info/PKG-INFO
strpy.egg-info/SOURCES.txt
strpy.egg-info/dependency_links.txt
strpy.egg-info/requires.txt
strpy.egg-info/top_level.txt
strpy/bobo/__init__.py
strpy/bobo/analysis.py
strpy/bobo/annotation.py
strpy/bobo/app.py
strpy/bobo/cache.py
strpy/bobo/camera.py
strpy/bobo/classification.py
strpy/bobo/cluster.py
strpy/bobo/flickr.py
strpy/bobo/geometry.py
strpy/bobo/image.py
strpy/bobo/imagesearch.py
strpy/bobo/linalg.py
strpy/bobo/math.py
strpy/bobo/matlab.py
strpy/bobo/metrics.py
strpy/bobo/partition.py
strpy/bobo/play.py
strpy/bobo/rdd.py
strpy/bobo/recognition.py
strpy/bobo/scene.py
strpy/bobo/show.py
strpy/bobo/stream.py
strpy/bobo/upload.py
strpy/bobo/util.py
strpy/bobo/video.py
strpy/bobo/videosearch.py
strpy/bobo/gui/__init__.py
strpy/bobo/gui/using_matplotlib.py
strpy/bobo/gui/using_opencv.py
strpy/bobo/gui/using_pygame.py
strpy/bobo/viset/__init__.py
strpy/bobo/viset/aflw.py
strpy/bobo/viset/archive.py
strpy/bobo/viset/caltech101.py
strpy/bobo/viset/caltech256.py
strpy/bobo/viset/download.py
strpy/bobo/viset/ethzshapes.py
strpy/bobo/viset/ethzshapes_extended.py
strpy/bobo/viset/fddb.py
strpy/bobo/viset/hmdb.py
strpy/bobo/viset/imagenet.py
strpy/bobo/viset/janus_gallery.py
strpy/bobo/viset/kthactions.py
strpy/bobo/viset/labelme.py
strpy/bobo/viset/mnist.py
strpy/bobo/viset/pascalvoc.py
strpy/bobo/viset/stream.py
strpy/bobo/viset/videodir.py
strpy/bobo/viset/demo/demo_caltech101.py
strpy/bobo/viset/demo/demo_caltech256.py
strpy/bobo/viset/demo/demo_categorization.py
strpy/bobo/viset/demo/demo_ethzshapes.py
strpy/bobo/viset/demo/demo_ethzshapes_extended.py
strpy/bobo/viset/demo/demo_imagedir.py
strpy/bobo/viset/demo/demo_imagenet.py
strpy/bobo/viset/demo/demo_labelme.py
strpy/bobo/viset/demo/demo_pascalvoc.py
strpy/image/__init__.py
strpy/image/ssim.py
strpy/janus/__init__.py
strpy/janus/bcubed.py
strpy/janus/cache.py
strpy/janus/classifier.py
strpy/janus/cluster.py
strpy/janus/crossval_optimization.py
strpy/janus/detection.py
strpy/janus/detection_quality.py
strpy/janus/dq.py
strpy/janus/encoding.py
