Metadata-Version: 1.1
Name: strpy
Version: 0.6.5
Summary: STR python tools for computer vision and machine learning
Home-page: https://github.com/stresearch/strpy
Author: Jeffrey Byrne
Author-email: jeffrey.byrne@stresearch.com
License: UNKNOWN
Download-URL: https://github.com/stresearch/strpy/archive/0.6.5.tar.gz
Keywords: STR,vision,learning,janus
Platform: UNKNOWN
